rarelink/.DS_Store
rarelink/__init__.py
rarelink/__main__.py
rarelink/_versions.py
rarelink/cli/__init__.py
rarelink/cli/fhir/__init__.py
rarelink/cli/fhir/export.py
rarelink/cli/fhir/hapi_server.py
rarelink/cli/fhir/restart_dockers.py
rarelink/cli/fhir/setup.py
rarelink/cli/framework/__init__.py
rarelink/cli/framework/reset.py
rarelink/cli/framework/status.py
rarelink/cli/framework/update.py
rarelink/cli/framework/version.py
rarelink/cli/phenopackets/__init__.py
rarelink/cli/phenopackets/export.py
rarelink/cli/redcap/__init__.py
rarelink/cli/redcap/download_records.py
rarelink/cli/redcap/fetch_metadata.py
rarelink/cli/redcap/upload_records.py
rarelink/cli/redcap/validate_hgvs.py
rarelink/cli/setup/__init__.py
rarelink/cli/setup/data_dictionary.py
rarelink/cli/setup/keys.py
rarelink/cli/setup/redcap_project.py
rarelink/cli/setup/reset.py
rarelink/cli/setup/view.py
rarelink/cli/utils/__init__.py
rarelink/cli/utils/file_utils.py
rarelink/cli/utils/logging_utils.py
rarelink/cli/utils/pipeline_utils.py
rarelink/cli/utils/string_utils.py
rarelink/cli/utils/terminal_utils.py
rarelink/cli/utils/validation_utils.py
rarelink/cli/utils/write_utils.py
rarelink/phenopackets/__init__.py
rarelink/phenopackets/create.py
rarelink/phenopackets/pipeline.py
rarelink/phenopackets/validate.py
rarelink/phenopackets/write.py
rarelink/phenopackets/adapter/__init__.py
rarelink/phenopackets/adapter/multi_onset.py
rarelink/phenopackets/mappings/base_mapper.py
rarelink/phenopackets/mappings/disease_mapper.py
rarelink/phenopackets/mappings/individual_mapper.py
rarelink/phenopackets/mappings/interpretation_mapper.py
rarelink/phenopackets/mappings/measurement_mapper.py
rarelink/phenopackets/mappings/medical_action_mapper.py
rarelink/phenopackets/mappings/metadata_mapper.py
rarelink/phenopackets/mappings/phenotypic_feature_mapper.py
rarelink/phenopackets/mappings/variation_descriptor_mapper.py
rarelink/phenopackets/mappings/vital_status_mapper.py
rarelink/phenopackets/mappings/utils/__init__.py
rarelink-2.0.5.dist-info/licenses/LICENSE
rarelink-2.0.5.dist-info/METADATA
rarelink-2.0.5.dist-info/WHEEL
rarelink-2.0.5.dist-info/entry_points.txt
rarelink-2.0.5.dist-info/top_level.txt
rarelink-2.0.5.dist-info/RECORD
