Metadata-Version: 2.4
Name: rarelink
Version: 2.0.5
Summary: RareLink - A REDCap-based Python framework linking international registries to HL7 FHIR and GA4GH Phenopackets
Author-email: Adam SL Graefe <adam.graefe@charite.de>, Filip Rehburg <filip.rehburg@charite.de>, Samer Alkarkoukly <mabbouda@uni-koeln.de>, Daniel Danis <daniel.danis@bih-charite.de>, Melissa A Haendel <mhaendel@email.unc.edu>, Peter N Robinson <peter.robinson@bih-charite.de>, Sylvia Thun <sylvia.thun@bih-charite.de>, Oya Beyan <oya.beyan@uni-koeln.de>
License:                                  Apache License
Project-URL: Homepage, https://github.com/BIH-CEI/RareLink
Project-URL: Repository, https://github.com/BIH-CEI/RareLink.git
Project-URL: Documentation, https://rarelink.readthedocs.io/en/latest/
Project-URL: Bugtracker, https://github.com/BIH-CEI/RareLink/issues
Keywords: Rare Disease,Interoperability,FHIR,Phenopacket Schema,REDCap
Classifier: License :: OSI Approved :: Apache Software License
Classifier: Operating System :: OS Independent
Classifier: Development Status :: 3 - Alpha
Classifier: Programming Language :: Python :: 3.10
Classifier: Programming Language :: Python :: 3.11
Classifier: Programming Language :: Python :: 3.12
Classifier: Intended Audience :: Science/Research
Classifier: Topic :: Scientific/Engineering :: Medical Science Apps.
Requires-Python: <3.13,>=3.10
License-File: LICENSE
Requires-Dist: numpy
Requires-Dist: pandas
Requires-Dist: phenopackets
Requires-Dist: pyphetools
Requires-Dist: pytest
Requires-Dist: requests
Requires-Dist: config
Requires-Dist: sphinx-autobuild
Requires-Dist: sphinx-copybutton
Requires-Dist: sphinx-rtd-theme
Requires-Dist: typer
Requires-Dist: pytest-mock
Requires-Dist: tqdm
Requires-Dist: node
Requires-Dist: npm
Requires-Dist: linkml>=1.9.0
Requires-Dist: linkml-runtime>=1.9.0
Requires-Dist: pydantic<2.11
Requires-Dist: schema-automator
Requires-Dist: python-dotenv
Requires-Dist: docker
Requires-Dist: rd-cdm>=2.0.2
Provides-Extra: test
Requires-Dist: pytest<9,>=7; extra == "test"
Requires-Dist: pytest-mock; extra == "test"
Provides-Extra: docs
Requires-Dist: sphinx>=7; extra == "docs"
Requires-Dist: sphinx-rtd-theme>=1.3; extra == "docs"
Requires-Dist: sphinx-copybutton>=0.5; extra == "docs"
Provides-Extra: dev
Requires-Dist: build; extra == "dev"
Requires-Dist: twine; extra == "dev"
Requires-Dist: jupyter; extra == "dev"
Requires-Dist: sphinx>=7; extra == "dev"
Requires-Dist: sphinx-rtd-theme>=1.3; extra == "dev"
Requires-Dist: sphinx-copybutton>=0.5; extra == "dev"
Requires-Dist: pytest<9,>=7; extra == "dev"
Requires-Dist: pytest-mock; extra == "dev"
Requires-Dist: docker; extra == "dev"
Dynamic: license-file
